README.md
setup.py
hitotsu/__init__.py
hitotsu/print_f.py
hitotsu.egg-info/PKG-INFO
hitotsu.egg-info/SOURCES.txt
hitotsu.egg-info/dependency_links.txt
hitotsu.egg-info/top_level.txt