Metadata-Version: 1.0
Name: hitotsu
Version: 0.1.0
Summary: a library for hitotsu
Home-page: UNKNOWN
Author: d
Author-email: UNKNOWN
License: BSD License
Keywords: hitotsu
Platform: any
